LICENSE.txt
README.md
setup.cfg
setup.py
TonHelpers/__init__.py
TonHelpers/helper.py
TonHelpers.egg-info/PKG-INFO
TonHelpers.egg-info/SOURCES.txt
TonHelpers.egg-info/dependency_links.txt
TonHelpers.egg-info/requires.txt
TonHelpers.egg-info/top_level.txt