Metadata-Version: 2.1
Name: TonHelpers
Version: 1.0.0
Summary: Funções denomidas Helpers para ajudar da otimização
Home-page: https://github.com/yanorestes/aluratemp
Author: Eriton Gomes De Souza
Author-email: eriton.gomes.souza@gmail.com
License: MIT
Project-URL: Código fonte, https://github.com/yanorestes/aluratemp
Project-URL: Download, https://github.com/yanorestes/aluratemp/archive/1.0.0.zip
Keywords: Função otimização
Requires-Python: >=3.6
License-File: LICENSE.txt
Requires-Dist: requests>=2.25.1
Requires-Dist: numpy
Requires-Dist: pandas
Requires-Dist: pytest==8.3.3
